SPARQLToSQL/Classes.py
SPARQLToSQL/RDFClasses.py
SPARQLToSQL/RelationalClasses.py
SPARQLToSQL/SparqlLexer.py
SPARQLToSQL/SparqlParser.py
SPARQLToSQL/__init__.py
SPARQLToSQL/auxiliary_functions.py
SPARQLToSQL/capitals.db
SPARQLToSQL/capitals.rdf
SPARQLToSQL/constants.py
SPARQLToSQL/controller.py
SPARQLToSQL/create_table.sql
SPARQLToSQL/currencies.db
SPARQLToSQL/currencies.rdf
SPARQLToSQL/main.py
SPARQLToSQL/mapping.py
SPARQLToSQL/parser_helper.py
SPARQLToSQL/persons.db
SPARQLToSQL/persons.sql
SPARQLToSQL/routing.py
SPARQLToSQL/sql_functions.py
SPARQLToSQL/sql_helper.py
SPARQLToSQL/sqlite.py
SPARQLToSQL/translation_helper.py
SPARQLToSQL/translator.py
SPARQLToSQL/rdf/capitals.rdf
SPARQLToSQL/rdf/currencies.rdf
SPARQLToSQL/sql/create_table.sql
SPARQLToSQL/sql/persons.sql
SPARQLToSQL/static/css/style.css
SPARQLToSQL/static/img/bg-white.gif
SPARQLToSQL/static/js/angular.js
SPARQLToSQL/static/js/translatorApp.js
SPARQLToSQL/templates/index.html
SPARQLToSQL-1.0.2.dist-info/DESCRIPTION.rst
SPARQLToSQL-1.0.2.dist-info/METADATA
SPARQLToSQL-1.0.2.dist-info/RECORD
SPARQLToSQL-1.0.2.dist-info/WHEEL
SPARQLToSQL-1.0.2.dist-info/entry_points.txt
SPARQLToSQL-1.0.2.dist-info/metadata.json
SPARQLToSQL-1.0.2.dist-info/top_level.txt
